pyenvisalink/__init__.py
pyenvisalink/alarm_panel.py
pyenvisalink/alarm_state.py
pyenvisalink/dsc_client.py
pyenvisalink/dsc_envisalinkdefs.py
pyenvisalink/envisalink_base_client.py
pyenvisalink/honeywell_client.py
pyenvisalink/honeywell_envisalinkdefs.py
pyenvisalink/test_harness.py
pyenvisalink-4.8.dist-info/LICENSE.txt
pyenvisalink-4.8.dist-info/METADATA
pyenvisalink-4.8.dist-info/WHEEL
pyenvisalink-4.8.dist-info/top_level.txt
pyenvisalink-4.8.dist-info/RECORD
