Metadata-Version: 2.1
Name: pyenvisalink
Version: 4.8
Summary: A python3 library for running asynchronus communications with envisalink alarm control panel modules.
Home-page: https://github.com/ufodone/pyenvisalink
Author: David O'Neill
Author-email: ufodone@gmail.com
License: MIT
Classifier: Development Status :: 4 - Beta
Classifier: Programming Language :: Python :: 3.10
License-File: LICENSE.txt
